imatlab/__init__.py
imatlab/__main__.py
imatlab/_exporter.py
imatlab/_kernel.py
imatlab/_redirection.py
imatlab/_version.py
imatlab/data/imatlab_export_fig.m
imatlab/data/matlab.tpl
imatlab-0.4.dist-info/LICENSE.txt
imatlab-0.4.dist-info/METADATA
imatlab-0.4.dist-info/RECORD
imatlab-0.4.dist-info/WHEEL
imatlab-0.4.dist-info/entry_points.txt
imatlab-0.4.dist-info/top_level.txt
