Metadata-Version: 2.1
Name: imatlab
Version: 0.4
Summary: A Juyter kernel for MATLAB.
Home-page: https://github.com/imatlab/imatlab
Author: Antony Lee
License: MIT
Platform: UNKNOWN
Classifier: Framework :: IPython
Classifier: License :: OSI Approved :: MIT License
Classifier: Programming Language :: Python :: 3.5
Classifier: Programming Language :: Python :: 3.6
Classifier: Topic :: System :: Shells
Requires-Python: >=3.5
Requires-Dist: ipykernel (>=4.1)
Requires-Dist: nbconvert (>=4.2)
Requires-Dist: plotly (>=1.13.0)
Requires-Dist: widgetsnbextension (>=1.0)
Requires-Dist: matlabengineforpython (>=R2016b)
